CHANGELOG.txt
LICENCE.txt
MANIFEST.in
README.txt
setup.py
qapGAr/Crossover.py
qapGAr/Fitness.py
qapGAr/GeneratePopulation.py
qapGAr/GeneticAlgorithm.py
qapGAr/Mutation.py
qapGAr/Problem.py
qapGAr/Selection.py
qapGAr/__init__.py
qapGAr.egg-info/PKG-INFO
qapGAr.egg-info/SOURCES.txt
qapGAr.egg-info/dependency_links.txt
qapGAr.egg-info/top_level.txt