Metadata-Version: 2.1
Name: qapGAr
Version: 0.0.1
Summary: genetic algorithm library for quadratic assignment problem
Home-page: 
Author: Rūta Buckiūnaitė
Author-email: aneliukee@gmail.com
License: MIT
Keywords: genetic,algorithm,quadratic,assignment
Platform: UNKNOWN
Classifier: Development Status :: 5 - Production/Stable
Classifier: Intended Audience :: Education
Classifier: Operating System :: Microsoft :: Windows :: Windows 10
Classifier: License :: OSI Approved :: MIT License
Classifier: Programming Language :: Python
License-File: LICENCE.txt
